nemo_eval/__init__.py
nemo_eval/api.py
nemo_eval/package_info.py
nemo_eval/utils/__init__.py
nemo_eval/utils/base.py
nemo_eval-0.1.0.dist-info/licenses/LICENSE
nemo_eval-0.1.0.dist-info/METADATA
nemo_eval-0.1.0.dist-info/WHEEL
nemo_eval-0.1.0.dist-info/top_level.txt
nemo_eval-0.1.0.dist-info/RECORD
