Metadata-Version: 2.4
Name: nemo-eval
Version: 0.1.0
Summary: NeMo Eval: Evaluation Utilities for LLM and VLM models
Author-email: NVIDIA <nemo-toolkit@nvidia.com>
Maintainer-email: NVIDIA <nemo-toolkit@nvidia.com>
License:                                  Apache License
Project-URL: Download, https://github.com/NVIDIA-NeMo/Eval/releases
Project-URL: Homepage, https://github.com/NVIDIA-NeMo/Eval
Keywords: NLP,NeMo,deep,gpu,language,learning,machine,nvidia,pytorch,torch
Classifier: Development Status :: 5 - Production/Stable
Classifier: Environment :: Console
Classifier: Intended Audience :: Developers
Classifier: Intended Audience :: Information Technology
Classifier: Intended Audience :: Science/Research
Classifier: License :: OSI Approved :: Apache Software License
Classifier: Natural Language :: English
Classifier: Operating System :: OS Independent
Classifier: Programming Language :: Python :: 3
Classifier: Programming Language :: Python :: 3.10
Classifier: Topic :: Scientific/Engineering :: Artificial Intelligence
Classifier: Topic :: Scientific/Engineering :: Image Recognition
Classifier: Topic :: Scientific/Engineering :: Mathematics
Classifier: Topic :: Scientific/Engineering
Classifier: Topic :: Software Development :: Libraries :: Python Modules
Classifier: Topic :: Software Development :: Libraries
Classifier: Topic :: Utilities
Requires-Python: <3.13,>=3.10
License-File: LICENSE
Requires-Dist: nvidia-lm-eval==25.7.1
Requires-Dist: nvidia-eval-commons~=1.0.0
Requires-Dist: uvicorn
Requires-Dist: flask
Dynamic: license-file
